aisqlite/__init__.py
aisqlite/main.py
aisqlite-1.1.0.dist-info/METADATA
aisqlite-1.1.0.dist-info/WHEEL
aisqlite-1.1.0.dist-info/top_level.txt
aisqlite-1.1.0.dist-info/RECORD
